django_accounts/__init__.py
djulcac_django_accounts-0.0.1.dist-info/LICENSE
djulcac_django_accounts-0.0.1.dist-info/METADATA
djulcac_django_accounts-0.0.1.dist-info/WHEEL
djulcac_django_accounts-0.0.1.dist-info/top_level.txt
djulcac_django_accounts-0.0.1.dist-info/RECORD
