Metadata-Version: 2.1
Name: djulcac-django-accounts
Version: 0.0.1
Summary: Accounts manager for django
Author-email: Danny Julca Carhuaz <djulcac@uni.pe>
Project-URL: Homepage, https://github.com/djulcac/django-accounts
Project-URL: Issues, https://github.com/djulcac/django-accounts/issues
Classifier: Programming Language :: Python :: 3
Classifier: License :: OSI Approved :: MIT License
Classifier: Operating System :: OS Independent
Requires-Python: >=3.8
License-File: LICENSE
